setup.py
wpas.py
wpas.egg-info/PKG-INFO
wpas.egg-info/SOURCES.txt
wpas.egg-info/dependency_links.txt
wpas.egg-info/entry_points.txt
wpas.egg-info/requires.txt
wpas.egg-info/top_level.txt