Metadata-Version: 1.1
Name: wpas
Version: 0.1
Summary: Command line tool for simple wpa_supplicant management
Home-page: http://github.com/tarruda/wpas
Author: Thiago de Arruda
Author-email: tpadilha84@gmail.com
License: MIT
Download-URL: https://github.com/tarruda/wpas/archive/0.1.tar.gz
Platform: UNKNOWN
